LICENSE
MANIFEST.in
README.rst
buildout.cfg
develop.cfg
pyproject.toml
requirements.txt
setup.py
version.txt
bob/__init__.py
bob.ip.gabor.egg-info/PKG-INFO
bob.ip.gabor.egg-info/SOURCES.txt
bob.ip.gabor.egg-info/dependency_links.txt
bob.ip.gabor.egg-info/not-zip-safe
bob.ip.gabor.egg-info/requires.txt
bob.ip.gabor.egg-info/top_level.txt
bob/ip/__init__.py
bob/ip/gabor/__init__.py
bob/ip/gabor/auxiliar.py
bob/ip/gabor/graph.cpp
bob/ip/gabor/jet.cpp
bob/ip/gabor/jet_statistics.cpp
bob/ip/gabor/main.cpp
bob/ip/gabor/similarity.cpp
bob/ip/gabor/test.py
bob/ip/gabor/test_picklability.py
bob/ip/gabor/transform.cpp
bob/ip/gabor/version.cpp
bob/ip/gabor/wavelet.cpp
bob/ip/gabor/cpp/Graph.cpp
bob/ip/gabor/cpp/Jet.cpp
bob/ip/gabor/cpp/JetStatistics.cpp
bob/ip/gabor/cpp/Similarity.cpp
bob/ip/gabor/cpp/Transform.cpp
bob/ip/gabor/cpp/Wavelet.cpp
bob/ip/gabor/data/gwt.hdf5
bob/ip/gabor/data/testgraph.hdf5
bob/ip/gabor/data/testimage.hdf5
bob/ip/gabor/data/testjet.hdf5
bob/ip/gabor/data/testjets.hdf5
bob/ip/gabor/data/testsim.hdf5
bob/ip/gabor/include/bob.ip.gabor/Graph.h
bob/ip/gabor/include/bob.ip.gabor/Jet.h
bob/ip/gabor/include/bob.ip.gabor/JetStatistics.h
bob/ip/gabor/include/bob.ip.gabor/Similarity.h
bob/ip/gabor/include/bob.ip.gabor/Transform.h
bob/ip/gabor/include/bob.ip.gabor/Wavelet.h
bob/ip/gabor/include/bob.ip.gabor/api.h
bob/ip/gabor/include/bob.ip.gabor/config.h
doc/c_cpp_api.rst
doc/conf.py
doc/guide.rst
doc/index.rst
doc/links.rst
doc/py_api.rst
doc/plot/disparity.py
doc/plot/similarity.py
doc/plot/transform.py
doc/plot/wavelet.py