Metadata-Version: 1.1
Name: bob.ip.gabor
Version: 2.0.18
Summary: Gabor wavelet analysis tools for Bob
Home-page: http://gitlab.idiap.ch/bob/bob.ip.gabor
Author: Manuel Guenther
Author-email: manuel.guenther@idiap.ch
License: BSD
Platform: UNKNOWN
Classifier: Framework :: Bob
Classifier: Development Status :: 4 - Beta
Classifier: Intended Audience :: Developers
Classifier: License :: OSI Approved :: BSD License
Classifier: Natural Language :: English
Classifier: Programming Language :: Python
Classifier: Programming Language :: Python :: 3
Classifier: Topic :: Software Development :: Libraries :: Python Modules
